{
  "_class": "symbolInstance",
  "booleanOperation": -1,
  "clippingMaskMode": 0,
  "do_objectID": "8D7636E0-936A-4DCB-B287-34B8F69435D2",
  "exportOptions": {
    "_class": "exportOptions",
    "do_objectID": "63937B20-7095-4B76-BF55-9B527C28E6FA",
    "exportFormats": [
    ],
    "includedLayerIds": [
    ],
    "layerOptions": 0,
    "shouldTrim": false
  },
  "frame": {
    "_class": "rect",
    "constrainProportions": false,
    "do_objectID": "B18D2DD9-48E5-4BCF-A888-90C65886B3CE",
    "height": 91,
    "width": 386,
    "x": 16,
    "y": 13
  },
  "hasClippingMask": false,
  "horizontalSpacing": 0,
  "isFixedToViewport": false,
  "isFlippedHorizontal": false,
  "isFlippedVertical": false,
  "isLocked": false,
  "isVisible": true,
  "layerListExpandedType": 0,
  "name": "Paper/Summary/Normal",
  "nameIsFixed": false,
  "overrideValues": [
  ],
  "resizingConstraint": 63,
  "resizingType": 0,
  "rotation": 0,
  "scale": 1,
  "shouldBreakMaskChain": false,
  "style": {
    "_class": "style",
    "do_objectID": "795A63F4-7F76-49A1-9B7A-F847998B877A",
    "endMarkerType": 0,
    "miterLimit": 10,
    "startMarkerType": 0,
    "windingRule": 1
  },
  "symbolID": "38F73CFC-5E52-4DCF-8CBC-54816E6B7779",
  "verticalSpacing": 0
}