{
  "_class": "group",
  "booleanOperation": -1,
  "clippingMaskMode": 0,
  "do_objectID": "F6410EF1-BE43-4694-B2BD-6CCEF3EA3715",
  "exportOptions": {
    "_class": "exportOptions",
    "do_objectID": "295457DF-6FF9-44CA-A2E4-CE0405E48D51",
    "exportFormats": [
    ],
    "includedLayerIds": [
    ],
    "layerOptions": 0,
    "shouldTrim": false
  },
  "frame": {
    "_class": "rect",
    "constrainProportions": false,
    "do_objectID": "E31FF715-0DD8-4273-AF8C-429606E5BC4B",
    "height": 48,
    "width": 282,
    "x": 0,
    "y": 37
  },
  "hasClickThrough": false,
  "hasClippingMask": false,
  "isFixedToViewport": false,
  "isFlippedHorizontal": false,
  "isFlippedVertical": false,
  "isLocked": false,
  "isVisible": true,
  "layerListExpandedType": 0,
  "layers": [
    {
      "class": "group",
      "id": "B87F9E32-C9B0-4249-822E-812055D0866C"
    },
    {
      "class": "group",
      "id": "FE052F98-3491-4707-915A-97CAA9CB17A8"
    },
    {
      "class": "rectangle",
      "id": "05E87A0D-C035-4D64-BDC1-78065425951B"
    }
  ],
  "name": "Group 18",
  "nameIsFixed": false,
  "resizingConstraint": 63,
  "resizingType": 0,
  "rotation": 0,
  "shouldBreakMaskChain": false,
  "style": {
    "_class": "style",
    "do_objectID": "5E391E0B-FBE1-4382-94A2-6AB164AC2516",
    "endMarkerType": 0,
    "miterLimit": 10,
    "startMarkerType": 0,
    "windingRule": 1
  }
}