{
  "_class": "group",
  "booleanOperation": -1,
  "clippingMaskMode": 0,
  "do_objectID": "A19BA566-784A-4503-A06D-D67D6D8799AE",
  "exportOptions": {
    "_class": "exportOptions",
    "do_objectID": "5EB7F273-32CB-4521-92C3-CBCE27299B34",
    "exportFormats": [
    ],
    "includedLayerIds": [
    ],
    "layerOptions": 0,
    "shouldTrim": false
  },
  "frame": {
    "_class": "rect",
    "constrainProportions": false,
    "do_objectID": "12CA8F0B-72F7-493A-86A2-3909C3E85013",
    "height": 12,
    "width": 11,
    "x": 324,
    "y": 3
  },
  "hasClickThrough": false,
  "hasClippingMask": false,
  "isFixedToViewport": false,
  "isFlippedHorizontal": false,
  "isFlippedVertical": false,
  "isLocked": false,
  "isVisible": true,
  "layerListExpandedType": 0,
  "layers": [
    {
      "class": "group",
      "id": "9D461D59-ED38-4D07-A7FE-843EA799DCFB"
    },
    {
      "class": "slice",
      "id": "47F726F6-8B03-4514-AB6A-66EC385C6EA8"
    }
  ],
  "name": "Group 2 Copy 3",
  "nameIsFixed": false,
  "resizingConstraint": 63,
  "resizingType": 0,
  "rotation": 0,
  "shouldBreakMaskChain": false,
  "style": {
    "_class": "style",
    "do_objectID": "4EDE6A3B-EF77-46DF-B768-16E5D76B30B5",
    "endMarkerType": 0,
    "miterLimit": 10,
    "startMarkerType": 0,
    "windingRule": 1
  }
}