{
  "_class": "group",
  "booleanOperation": -1,
  "clippingMaskMode": 0,
  "do_objectID": "69A4E7E0-0EC9-4E98-B2DE-D2A025788C63",
  "exportOptions": {
    "_class": "exportOptions",
    "do_objectID": "EE3C8AB2-BF02-4B0B-B04C-14E28A884E9A",
    "exportFormats": [
    ],
    "includedLayerIds": [
    ],
    "layerOptions": 0,
    "shouldTrim": false
  },
  "frame": {
    "_class": "rect",
    "constrainProportions": false,
    "do_objectID": "6060C6B5-C5FD-42BF-989C-92C065014A88",
    "height": 51,
    "width": 156,
    "x": 328,
    "y": 31
  },
  "hasClickThrough": false,
  "hasClippingMask": false,
  "isFixedToViewport": false,
  "isFlippedHorizontal": false,
  "isFlippedVertical": false,
  "isLocked": false,
  "isVisible": true,
  "layerListExpandedType": 2,
  "layers": [
    {
      "class": "rectangle",
      "id": "DB8BF60D-0EAC-4793-AAC2-C2B092B5579D"
    },
    {
      "class": "text",
      "id": "DE1C9411-3EC8-4845-9533-8446C9037430"
    },
    {
      "class": "text",
      "id": "912EBF51-34B2-43D6-A5BF-81C2DC597321"
    },
    {
      "class": "group",
      "id": "DDE0B964-FFAF-45EA-9092-2959427F07CE"
    }
  ],
  "name": "Group 6 Copy 2",
  "nameIsFixed": false,
  "resizingConstraint": 63,
  "resizingType": 0,
  "rotation": 0,
  "shouldBreakMaskChain": false,
  "style": {
    "_class": "style",
    "do_objectID": "A59476B8-0809-4220-BA67-FE3A60E0603B",
    "endMarkerType": 0,
    "miterLimit": 10,
    "startMarkerType": 0,
    "windingRule": 1
  }
}