{
  "_class": "shapeGroup",
  "booleanOperation": -1,
  "clippingMaskMode": 0,
  "do_objectID": "C73A769B-D660-4FCF-B951-16F09B16C78A",
  "exportOptions": {
    "_class": "exportOptions",
    "do_objectID": "2BD3D70F-D642-4BC9-AC27-F2F328DC69CD",
    "exportFormats": [
    ],
    "includedLayerIds": [
    ],
    "layerOptions": 0,
    "shouldTrim": false
  },
  "frame": {
    "_class": "rect",
    "constrainProportions": false,
    "do_objectID": "B1A9AD74-1782-4FE3-8C3B-689A7139897F",
    "height": 9,
    "width": 12,
    "x": 4,
    "y": 9
  },
  "hasClickThrough": false,
  "hasClippingMask": true,
  "isFixedToViewport": false,
  "isFlippedHorizontal": false,
  "isFlippedVertical": false,
  "isLocked": false,
  "isVisible": true,
  "layerListExpandedType": 2,
  "layers": [
    {
      "class": "rectangle",
      "id": "4A8F5734-EF91-4FC8-9C91-E3A35A1D28A7"
    },
    {
      "class": "rectangle",
      "id": "1DD29215-956E-4C78-836C-16CF74643197"
    }
  ],
  "name": "Combined Shape",
  "nameIsFixed": false,
  "resizingConstraint": 63,
  "resizingType": 0,
  "rotation": 0,
  "shouldBreakMaskChain": false,
  "style": {
    "_class": "style",
    "borders": [
      {
        "_class": "border",
        "color": {
          "_class": "color",
          "alpha": 1,
          "blue": 0.207843137254902,
          "green": 0.1647058823529412,
          "red": 0.1176470588235294
        },
        "fillType": 0,
        "isEnabled": false,
        "position": 0,
        "thickness": 1
      }
    ],
    "do_objectID": "B7821A83-77C0-4B3C-BAC0-D11322A70320",
    "endMarkerType": 0,
    "fills": [
      {
        "_class": "fill",
        "color": {
          "_class": "color",
          "alpha": 1,
          "blue": 0.207843137254902,
          "green": 0.1647058823529412,
          "red": 0.1176470588235294
        },
        "fillType": 0,
        "isEnabled": true,
        "noiseIndex": 0,
        "noiseIntensity": 0,
        "patternFillType": 1,
        "patternTileScale": 1
      }
    ],
    "miterLimit": 10,
    "startMarkerType": 0,
    "windingRule": 0
  },
  "windingRule": 0
}