{
  "_class": "group",
  "booleanOperation": -1,
  "clippingMaskMode": 0,
  "do_objectID": "3C036EBB-0605-4E73-BDD1-3F6BC227BDF3",
  "exportOptions": {
    "_class": "exportOptions",
    "do_objectID": "5330E302-F3EF-41B5-B98F-5BABF6556A0D",
    "exportFormats": [
    ],
    "includedLayerIds": [
    ],
    "layerOptions": 0,
    "shouldTrim": false
  },
  "frame": {
    "_class": "rect",
    "constrainProportions": false,
    "do_objectID": "06F772D6-8AB4-4630-A0A2-8EEC4DE6CCC8",
    "height": 37,
    "width": 110,
    "x": 0,
    "y": 133
  },
  "hasClickThrough": false,
  "hasClippingMask": false,
  "isFixedToViewport": false,
  "isFlippedHorizontal": false,
  "isFlippedVertical": false,
  "isLocked": false,
  "isVisible": true,
  "layerListExpandedType": 0,
  "layers": [
    {
      "class": "text",
      "id": "4EA00671-2058-4A4D-BDDC-903904EEBD55"
    },
    {
      "class": "text",
      "id": "14A5FD6E-3C42-45FC-A466-B8E6AEBBDEDC"
    },
    {
      "class": "group",
      "id": "42C2BC55-5A38-48AE-83A8-3C3DFA571447"
    }
  ],
  "name": "Group 4 Copy",
  "nameIsFixed": false,
  "resizingConstraint": 63,
  "resizingType": 0,
  "rotation": 0,
  "shouldBreakMaskChain": false,
  "style": {
    "_class": "style",
    "do_objectID": "1298290F-7400-41B8-BF66-E8836EE8F821",
    "endMarkerType": 0,
    "miterLimit": 10,
    "startMarkerType": 0,
    "windingRule": 1
  }
}