{
  "_class": "group",
  "do_objectID": "B52F5A7A-8601-46FE-9C2E-0A2EACA7AFC6",
  "exportOptions": {
    "_class": "exportOptions",
    "do_objectID": "EC66C1F6-070B-4785-9E26-0CD44C0F29F4",
    "exportFormats": [
    ],
    "includedLayerIds": [
    ],
    "layerOptions": 0,
    "shouldTrim": false
  },
  "frame": {
    "_class": "rect",
    "constrainProportions": false,
    "do_objectID": "0A222AEE-83B5-4A44-A29B-25F0E64B313B",
    "height": 24,
    "width": 327,
    "x": 0,
    "y": 186
  },
  "hasClickThrough": false,
  "isFlippedHorizontal": false,
  "isFlippedVertical": false,
  "isLocked": false,
  "isVisible": true,
  "layerListExpandedType": 2,
  "layers": [
    {
      "class": "symbolInstance",
      "id": "416C4C94-34C7-4E21-86DC-E5E0CAAAC8F2"
    },
    {
      "class": "symbolInstance",
      "id": "B3B2DCC8-EF66-42DC-BDC0-9FFA5A012988"
    },
    {
      "class": "symbolInstance",
      "id": "29EC350F-DA81-40F2-AF44-7C22F1F48E09"
    },
    {
      "class": "symbolInstance",
      "id": "F572D8E7-8BB2-466B-9C5F-DDC61248D4A7"
    }
  ],
  "name": "Action Button",
  "nameIsFixed": true,
  "resizingConstraint": 63,
  "resizingType": 0,
  "rotation": 0,
  "shouldBreakMaskChain": false,
  "style": {
    "_class": "style",
    "do_objectID": "9A17ED60-AE1A-4643-8698-DAD67DD02EC7",
    "endDecorationType": 0,
    "miterLimit": 10,
    "startDecorationType": 0
  }
}