{
  "_class": "artboard",
  "backgroundColor": {
    "_class": "color",
    "alpha": 1,
    "blue": 1,
    "do_objectID": "A644F6DF-4909-4D9B-B8B4-676707F19DAC",
    "green": 1,
    "red": 1
  },
  "do_objectID": "22D35CEF-9C7C-42C1-B2F4-09A97D01D42D",
  "exportOptions": {
    "_class": "exportOptions",
    "do_objectID": "9B99B08B-181F-408B-A9CE-962B27B8B6E1",
    "exportFormats": [
      {
        "_class": "exportFormat",
        "absoluteSize": 0,
        "fileFormat": "png",
        "name": "",
        "namingScheme": 0,
        "scale": 2,
        "visibleScaleType": 0
      }
    ],
    "includedLayerIds": [
    ],
    "layerOptions": 0,
    "shouldTrim": false
  },
  "frame": {
    "_class": "rect",
    "constrainProportions": false,
    "do_objectID": "DC9030E0-18A1-4D31-8AE9-7B9E44B7A4AF",
    "height": 900,
    "width": 1440,
    "x": -10382,
    "y": 3694
  },
  "hasBackgroundColor": true,
  "hasClickThrough": true,
  "horizontalRulerData": {
    "_class": "rulerData",
    "base": 0,
    "do_objectID": "5A44B14F-F480-450B-A049-DF10C778AFA8",
    "guides": [
    ]
  },
  "includeBackgroundColorInExport": true,
  "includeInCloudUpload": true,
  "isFlippedHorizontal": false,
  "isFlippedVertical": false,
  "isFlowHome": false,
  "isLocked": false,
  "isVisible": true,
  "layerListExpandedType": 2,
  "layers": [
    {
      "class": "group",
      "id": "A58CFABE-C8ED-4B21-A330-1B8B041F3623"
    },
    {
      "class": "shapeGroup",
      "id": "41D58EB1-11E1-4E86-B4EB-B4450D550F38"
    },
    {
      "class": "shapeGroup",
      "id": "06164517-7ED9-4A56-B222-3B50CB73E12A"
    },
    {
      "class": "text",
      "id": "8C200056-ACCD-4408-B13A-E04CB4FC846C"
    },
    {
      "class": "text",
      "id": "9183792D-072C-4F72-ADED-FAC1DC30F297"
    },
    {
      "class": "text",
      "id": "DFA44678-EA4F-4187-A746-C7912F6169E5"
    },
    {
      "class": "text",
      "id": "EDE54228-E0B3-4FC1-A140-53CBEF983CEF"
    },
    {
      "class": "text",
      "id": "429FFCD8-5D9B-4641-8AF8-7ED71997186A"
    },
    {
      "class": "text",
      "id": "834F6377-BBDF-445B-9698-874617A011E3"
    },
    {
      "class": "symbolInstance",
      "id": "AAC24BE7-E992-4F22-B5AB-3517C1CE0C75"
    },
    {
      "class": "symbolInstance",
      "id": "C088F14F-8625-48A6-AB83-85B43DB05250"
    },
    {
      "class": "symbolInstance",
      "id": "60DE1BDD-6BE4-44A6-A465-634CFA8B4770"
    },
    {
      "class": "symbolInstance",
      "id": "ECA2D7ED-AE88-4C89-B3E0-113D15819AF3"
    },
    {
      "class": "symbolInstance",
      "id": "4CEF8D12-83FA-4E2C-944C-F7243CE6C0A7"
    },
    {
      "class": "symbolInstance",
      "id": "1CD73175-27CC-47A2-98A7-59844D29A2C9"
    },
    {
      "class": "symbolInstance",
      "id": "94C96077-9226-4DDF-9CF2-74F481974209"
    },
    {
      "class": "symbolInstance",
      "id": "866FEEA9-4B5B-478E-95B9-1271E2E6AACE"
    },
    {
      "class": "symbolInstance",
      "id": "B0A17CF0-9659-4878-ACC2-946F58EA27F8"
    },
    {
      "class": "symbolInstance",
      "id": "0A5A5FB5-D754-4396-97E2-A8476FCAB049"
    },
    {
      "class": "symbolInstance",
      "id": "2135B57C-E083-4333-984B-E5AA0D267C4D"
    },
    {
      "class": "symbolInstance",
      "id": "96EDF64B-41EE-4A6A-A91F-AA48BF7D15A1"
    },
    {
      "class": "group",
      "id": "C70F81C3-C156-4801-A2FB-C512D8FDF10D"
    },
    {
      "class": "symbolInstance",
      "id": "A46C4903-1608-485C-AE09-6C7F62617590"
    },
    {
      "class": "symbolInstance",
      "id": "83EAB48A-3581-449D-B71F-4842A3C3E48E"
    },
    {
      "class": "symbolInstance",
      "id": "74503E72-B5BC-4D43-A4A8-0B54BB986EC6"
    },
    {
      "class": "symbolInstance",
      "id": "2425307A-36F1-4588-99FD-323BCCD526D9"
    },
    {
      "class": "symbolInstance",
      "id": "4EFEB757-4904-46D2-B0F1-7892DBECFD62"
    },
    {
      "class": "symbolInstance",
      "id": "30A61C10-3F92-494C-8198-976980406B76"
    },
    {
      "class": "symbolInstance",
      "id": "4447E455-81E1-4315-B938-79B2DAEA3709"
    },
    {
      "class": "symbolInstance",
      "id": "C32C7547-36E6-4A3F-93C8-C23C0F5ECF81"
    },
    {
      "class": "symbolInstance",
      "id": "10E419A6-75AC-4E0F-B63F-025929324224"
    },
    {
      "class": "symbolInstance",
      "id": "DA84E198-9502-4F79-A3FD-5BFA13C4ABD6"
    },
    {
      "class": "symbolInstance",
      "id": "CE157509-D177-4D4B-AD22-DDEF9A7B8B56"
    },
    {
      "class": "symbolInstance",
      "id": "C9007E4F-78A9-4188-A08F-F080CB9CFAAA"
    },
    {
      "class": "text",
      "id": "5B2DA77D-0C11-4BC7-956B-1134B72FC583"
    },
    {
      "class": "text",
      "id": "171E6550-CAA0-4E3E-8E90-2533801BB152"
    },
    {
      "class": "symbolInstance",
      "id": "CCD59C14-FE53-4DB9-B231-48AAB61DE947"
    },
    {
      "class": "group",
      "id": "9B10625E-09D5-4753-95D7-94288A5E6771"
    },
    {
      "class": "symbolInstance",
      "id": "929F0AD0-CCC0-42AA-A15B-9BA6D7DDFD6B"
    },
    {
      "class": "group",
      "id": "F8E6CBEA-BEF4-4DF8-B561-8E52A4A23432"
    },
    {
      "class": "group",
      "id": "A5FE128A-5F29-4DCC-A4A9-14A638F05FC4"
    }
  ],
  "layout": {
    "_class": "layoutGrid",
    "columnWidth": 79.83333333333333,
    "do_objectID": "CBF94C74-66C6-4BBC-9C3F-5B6AF2E5138E",
    "drawHorizontal": false,
    "drawHorizontalLines": false,
    "drawVertical": true,
    "gutterHeight": 12,
    "gutterWidth": 22,
    "guttersOutside": false,
    "horizontalOffset": 120,
    "isEnabled": false,
    "numberOfColumns": 12,
    "rowHeightMultiplication": 5,
    "totalWidth": 1200
  },
  "name": "Papaer Show + Collection Copy",
  "nameIsFixed": true,
  "resizesContent": false,
  "resizingConstraint": 63,
  "resizingType": 0,
  "rotation": 0,
  "shouldBreakMaskChain": true,
  "style": {
    "_class": "style",
    "do_objectID": "CB3EB367-6E80-4E3B-AD6D-CE50B05F7A6F",
    "endDecorationType": 0,
    "fills": [
      {
        "_class": "fill",
        "color": {
          "_class": "color",
          "alpha": 1,
          "blue": 1,
          "green": 1,
          "red": 1
        },
        "fillType": 0,
        "isEnabled": true,
        "noiseIndex": 0,
        "noiseIntensity": 0,
        "patternFillType": 1,
        "patternTileScale": 1
      }
    ],
    "miterLimit": 10,
    "startDecorationType": 0
  },
  "userInfo": {
    "com.animaapp.stc-sketch-plugin": {
      "kModelPropertiesKey": {
      }
    }
  },
  "verticalRulerData": {
    "_class": "rulerData",
    "base": 0,
    "do_objectID": "9DEDA9EB-E84A-4D95-B32E-B9399BE6C3AD",
    "guides": [
    ]
  }
}