{
  "_class": "group",
  "booleanOperation": -1,
  "clippingMaskMode": 0,
  "do_objectID": "81BDF6BC-88F5-40D1-8503-98D583D459BC",
  "exportOptions": {
    "_class": "exportOptions",
    "do_objectID": "A7AA8930-B5C8-42EC-B25F-0CC818916B18",
    "exportFormats": [
    ],
    "includedLayerIds": [
    ],
    "layerOptions": 0,
    "shouldTrim": false
  },
  "frame": {
    "_class": "rect",
    "constrainProportions": false,
    "do_objectID": "931B88A6-6D21-449F-BC04-365A63D4596E",
    "height": 15,
    "width": 12,
    "x": 128,
    "y": 3
  },
  "hasClickThrough": false,
  "hasClippingMask": false,
  "isFixedToViewport": false,
  "isFlippedHorizontal": false,
  "isFlippedVertical": false,
  "isLocked": false,
  "isVisible": true,
  "layerListExpandedType": 0,
  "layers": [
    {
      "class": "rectangle",
      "id": "E4396555-80E7-4CEC-AC15-D5E1CEDBB774"
    },
    {
      "class": "text",
      "id": "5D4632AA-D014-4423-A0F6-AB1990A045B7"
    }
  ],
  "name": "Group 8",
  "nameIsFixed": false,
  "resizingConstraint": 63,
  "resizingType": 0,
  "rotation": 0,
  "shouldBreakMaskChain": false,
  "style": {
    "_class": "style",
    "do_objectID": "65FDF5DC-5EFA-4080-8243-5DC520E6CDEB",
    "endMarkerType": 0,
    "miterLimit": 10,
    "startMarkerType": 0,
    "windingRule": 1
  }
}