{
  "_class": "symbolInstance",
  "booleanOperation": 0,
  "clippingMaskMode": 0,
  "do_objectID": "AD250AC7-8FCD-469A-9586-04BF87247508",
  "exportOptions": {
    "_class": "exportOptions",
    "do_objectID": "D793F124-C27B-482A-ABD2-8F553520A447",
    "exportFormats": [
    ],
    "includedLayerIds": [
    ],
    "layerOptions": 0,
    "shouldTrim": false
  },
  "frame": {
    "_class": "rect",
    "constrainProportions": false,
    "do_objectID": "27B8B827-2C07-43F3-BB47-93D81C4E8661",
    "height": 20,
    "width": 302,
    "x": 16,
    "y": 7
  },
  "hasClippingMask": false,
  "horizontalSpacing": 0,
  "isFixedToViewport": false,
  "isFlippedHorizontal": false,
  "isFlippedVertical": false,
  "isLocked": false,
  "isVisible": true,
  "layerListExpandedType": 0,
  "name": "Text/Subheader/Disabled/Black",
  "nameIsFixed": false,
  "overrideValues": [
    {
      "_class": "overrideValue",
      "overrideName": "D9EA5C5B-E472-4A49-96CF-1B9D6C608355_stringValue",
      "value": "Search papers by title author, doi or keyword"
    }
  ],
  "resizingConstraint": 26,
  "resizingType": 0,
  "rotation": 0,
  "scale": 1,
  "shouldBreakMaskChain": false,
  "style": {
    "_class": "style",
    "do_objectID": "E6955D5A-AE91-4823-AAB3-78E0D7BFA35E",
    "endMarkerType": 0,
    "miterLimit": 10,
    "startMarkerType": 0,
    "windingRule": 1
  },
  "symbolID": "89D11861-9D3C-493C-840A-0ED17F7B2A89",
  "verticalSpacing": 0
}