{
  "_class": "symbolInstance",
  "booleanOperation": 0,
  "clippingMaskMode": 0,
  "do_objectID": "4AF4D1C8-705D-4078-BAB2-91C45E70B45F",
  "exportOptions": {
    "_class": "exportOptions",
    "exportFormats": [
    ],
    "includedLayerIds": [
    ],
    "layerOptions": 0,
    "shouldTrim": false
  },
  "frame": {
    "_class": "rect",
    "constrainProportions": true,
    "height": 32,
    "width": 32,
    "x": 58,
    "y": 8
  },
  "hasClippingMask": false,
  "horizontalSpacing": 0,
  "isFixedToViewport": false,
  "isFlippedHorizontal": false,
  "isFlippedVertical": false,
  "isLocked": false,
  "isVisible": true,
  "layerListExpandedType": 2,
  "name": "Loading",
  "nameIsFixed": false,
  "originalObjectID": "4AF4D1C8-705D-4078-BAB2-91C45E70B45F",
  "overrideValues": [
    {
      "_class": "overrideValue",
      "overrideName": "8D43651D-9D6E-4555-9703-AF8FD38362EF_symbolID",
      "value": "D25AB969-C46E-44B7-A81F-B931386EB467"
    }
  ],
  "resizingConstraint": 45,
  "resizingType": 3,
  "rotation": 0,
  "scale": 1,
  "shouldBreakMaskChain": false,
  "style": {
    "_class": "style",
    "endMarkerType": 0,
    "miterLimit": 10,
    "startMarkerType": 0,
    "windingRule": 1
  },
  "symbolID": "2D2C947F-52E7-49BE-9AD1-AEA5584A1CAF",
  "verticalSpacing": 0
}