{
  "_class": "group",
  "booleanOperation": -1,
  "clippingMaskMode": 0,
  "do_objectID": "FAA70707-2AE0-4C25-B1E7-958B8BCF7BCB",
  "exportOptions": {
    "_class": "exportOptions",
    "do_objectID": "A1D2D606-60A0-4392-B538-21558CFE22DE",
    "exportFormats": [
    ],
    "includedLayerIds": [
    ],
    "layerOptions": 0,
    "shouldTrim": false
  },
  "frame": {
    "_class": "rect",
    "constrainProportions": false,
    "do_objectID": "780B0032-7413-493A-B1E5-439615B5873B",
    "height": 49,
    "width": 424,
    "x": 0,
    "y": 0
  },
  "hasClickThrough": false,
  "hasClippingMask": false,
  "isFixedToViewport": false,
  "isFlippedHorizontal": false,
  "isFlippedVertical": false,
  "isLocked": false,
  "isVisible": true,
  "layerListExpandedType": 2,
  "layers": [
    {
      "class": "group",
      "id": "B153FB87-2E21-49ED-A4A7-E28F6B7F5587"
    },
    {
      "class": "rectangle",
      "id": "C2166D8C-69F0-439D-A2E4-4A1322EB4753"
    }
  ],
  "name": "Group 14",
  "nameIsFixed": false,
  "resizingConstraint": 63,
  "resizingType": 0,
  "rotation": 0,
  "shouldBreakMaskChain": false,
  "style": {
    "_class": "style",
    "do_objectID": "A2CF4263-78A8-4359-91C0-1FD01893A0A7",
    "endMarkerType": 0,
    "miterLimit": 10,
    "startMarkerType": 0,
    "windingRule": 1
  }
}