{
  "_class": "bitmap",
  "booleanOperation": -1,
  "clippingMask": "{{0, 0}, {1, 1}}",
  "clippingMaskMode": 0,
  "do_objectID": "11938328-F7F0-410E-AD83-D5DEC9E0654E",
  "exportOptions": {
    "_class": "exportOptions",
    "do_objectID": "F9C5B20A-4FA6-429F-B1BC-0A7266B24B4E",
    "exportFormats": [
    ],
    "includedLayerIds": [
    ],
    "layerOptions": 0,
    "shouldTrim": false
  },
  "fillReplacesImage": false,
  "frame": {
    "_class": "rect",
    "constrainProportions": true,
    "do_objectID": "D07C6464-74A6-4757-90FF-85A6786434AF",
    "height": 359,
    "width": 595,
    "x": 0,
    "y": 0
  },
  "hasClippingMask": false,
  "image": {
    "_class": "MSJSONFileReference",
    "_ref": "images/a6735e0027e0b0ae3886b4d25c63a30e1eeca01b.png",
    "_ref_class": "MSImageData"
  },
  "intendedDPI": 144,
  "isFixedToViewport": false,
  "isFlippedHorizontal": false,
  "isFlippedVertical": false,
  "isLocked": false,
  "isVisible": true,
  "layerListExpandedType": 0,
  "name": "Bitmap",
  "nameIsFixed": false,
  "resizingConstraint": 63,
  "resizingType": 0,
  "rotation": 0,
  "shouldBreakMaskChain": false,
  "style": {
    "_class": "style",
    "do_objectID": "A9D5BD26-C06B-46C6-8ABB-4999544D416B",
    "endMarkerType": 0,
    "miterLimit": 10,
    "startMarkerType": 0,
    "windingRule": 1
  }
}