{
  "_class": "shapeGroup",
  "clippingMaskMode": 0,
  "do_objectID": "41C8270F-426B-4A9D-BD92-936DE4E943EC",
  "exportOptions": {
    "_class": "exportOptions",
    "exportFormats": [
    ],
    "includedLayerIds": [
    ],
    "layerOptions": 0,
    "shouldTrim": false
  },
  "frame": {
    "_class": "rect",
    "constrainProportions": false,
    "height": 71,
    "width": 6,
    "x": 120,
    "y": 17
  },
  "hasClickThrough": false,
  "hasClippingMask": false,
  "isFlippedHorizontal": false,
  "isFlippedVertical": false,
  "isLocked": false,
  "isVisible": true,
  "layerListExpandedType": 0,
  "layers": [
    {
      "class": "rectangle",
      "id": "6E8D42A0-4FFA-41ED-8FB0-61FC199B4012"
    }
  ],
  "name": "Bar",
  "nameIsFixed": false,
  "resizingConstraint": 45,
  "resizingType": 3,
  "rotation": 0,
  "shouldBreakMaskChain": false,
  "style": {
    "_class": "style",
    "do_objectID": "EA89FED2-F6F9-4354-91DE-51A54BC7F8BD",
    "endDecorationType": 0,
    "fills": [
      {
        "_class": "fill",
        "color": {
          "_class": "color",
          "alpha": 1,
          "blue": 1,
          "green": 0.5882352941176473,
          "red": 0.3764705882352941
        },
        "fillType": 0,
        "isEnabled": true,
        "noiseIndex": 0,
        "noiseIntensity": 0,
        "patternFillType": 0,
        "patternTileScale": 1
      }
    ],
    "miterLimit": 10,
    "sharedObjectID": "240369B7-455E-4F82-98A7-F0D9E505C57A",
    "startDecorationType": 0
  },
  "userInfo": {
    "com.animaapp.stc-sketch-plugin": {
      "kModelPropertiesKey": {
      }
    }
  },
  "windingRule": 1
}