{
  "_class": "group",
  "booleanOperation": -1,
  "clippingMaskMode": 0,
  "do_objectID": "71C97DA4-BF24-48E3-9FDD-B34464A50F07",
  "exportOptions": {
    "_class": "exportOptions",
    "do_objectID": "12F5F908-21DA-49E5-BF28-6ED935B7B3BB",
    "exportFormats": [
    ],
    "includedLayerIds": [
    ],
    "layerOptions": 0,
    "shouldTrim": false
  },
  "frame": {
    "_class": "rect",
    "constrainProportions": false,
    "do_objectID": "2786C512-AC90-4D84-A470-1302FA7DCDF3",
    "height": 19,
    "width": 182,
    "x": 0,
    "y": 0
  },
  "hasClickThrough": false,
  "hasClippingMask": false,
  "isFixedToViewport": false,
  "isFlippedHorizontal": false,
  "isFlippedVertical": false,
  "isLocked": false,
  "isVisible": true,
  "layerListExpandedType": 2,
  "layers": [
    {
      "class": "text",
      "id": "3FC3F6B8-3DD5-474A-9CD1-7869C18640FC"
    }
  ],
  "name": "Group 16",
  "nameIsFixed": false,
  "resizingConstraint": 63,
  "resizingType": 0,
  "rotation": 0,
  "shouldBreakMaskChain": false,
  "style": {
    "_class": "style",
    "do_objectID": "EF60CB9C-1A2A-4580-A0FB-B7FC41E49F08",
    "endMarkerType": 0,
    "miterLimit": 10,
    "startMarkerType": 0,
    "windingRule": 1
  }
}